README.md
setup.py
vcfremapper/__init__.py
vcfremapper/__main__.py
vcfremapper/header.py
vcfremapper/info.py
vcfremapper/remap.py
vcfremapper/revcomp.py
vcfremapper/samples.py
vcfremapper/sort_vcf.py
vcfremapper/utils.py
vcfremapper/variant.py
vcfremapper/vcf.py
vcfremapper.egg-info/PKG-INFO
vcfremapper.egg-info/SOURCES.txt
vcfremapper.egg-info/dependency_links.txt
vcfremapper.egg-info/entry_points.txt
vcfremapper.egg-info/requires.txt
vcfremapper.egg-info/top_level.txt