Metadata-Version: 2.1
Name: vcfremapper
Version: 1.0.5
Summary: Package to map VCFs between genome builds
Home-page: https://github.com/jeremymcrae/vcfremapper
Author: Jeremy McRae
Author-email: jmcrae@illumina.com
License: MIT
Platform: UNKNOWN
Classifier: Development Status :: 4 - Beta
Classifier: Topic :: Scientific/Engineering :: Bio-Informatics
Classifier: License :: OSI Approved :: MIT License
